Metadata-Version: 1.0
Name: jquery
Version: 1.2.2
Summary: Jquery javascript library for TurboGears
Home-page: UNKNOWN
Author: Fred Lin
Author-email: gasolin+tg@gmail.com
License: MIT
Keywords: turbogears.widgets
Platform: UNKNOWN
Classifier: Development Status :: 3 - Alpha
Classifier: Operating System :: OS Independent
Classifier: Programming Language :: Python
Classifier: Topic :: Software Development :: Libraries :: Python Modules
Classifier: Framework :: TurboGears
Classifier: Framework :: TurboGears :: Widgets
